{"name":"untitled","x":0,"y":0,"width":1280,"height":720,"theme":"Default Light","elements":[{"id":0,"type":0,"name":"Title","event":"","x":0,"y":0,"width":460,"height":80,"rotation":0,"text":"So Decadent","asset":"gothic.ttf","progress_at":0,"progress_total":100,"strength":1,"alignment":0,"anchor":0,"parent":null,"children":[],"visible":true,"color_text":-15458},{"id":1,"type":0,"name":"Selection","event":"","x":0,"y":40,"width":460,"height":50,"rotation":0,"text":"Click Your Selection","asset":"gothic.ttf","progress_at":0,"progress_total":100,"strength":1,"alignment":1,"anchor":1,"parent":2,"children":[],"visible":true,"color_text":4294951838},{"id":2,"type":3,"name":"Empty","event":"","x":0,"y":0,"width":460,"height":720,"rotation":0,"text":"My Empty","asset":"","progress_at":0,"progress_total":100,"strength":1,"alignment":2,"anchor":2,"parent":null,"children":[1],"visible":true}],"assets":[{"name":"LHANDW.TTF","file":"../../../../../../../../C:/WINDOWS/Fonts/LHANDW.TTF","id":0},{"name":"gothic.ttf","file":"../gothic.ttf","id":1}]}